<bibdata type="standard">
  <title type="title-main" format="text/plain" language="en" script="Latn">Permeability of membranes to water vapor with special reference to packaging materials/</title>
  <title type="main" format="text/plain" language="en" script="Latn">Permeability of membranes to water vapor with special reference to packaging materials/</title>
  <uri type="doi">https://nvlpubs.nist.gov/nistpubs/Legacy/MP/nbsmiscellaneouspub127.pdf</uri>
  <docidentifier type="NIST">NBS MP 127</docidentifier>
  <docidentifier type="DOI">10.6028/NBS.MP.127</docidentifier>
  <date type="published">
    <on>1937-01</on>
  </date>
  <contributor>
    <role type="author"/>
    <person>
      <name>
        <forename language="en" script="Latn">Frederick</forename>
        <surname language="en" script="Latn">Carson</surname>
      </name>
    </person>
  </contributor>
  <contributor>
    <role type="publisher"/>
    <organization>
      <name>National Institute of Standards and Technology</name>
      <abbreviation>NIST</abbreviation>
    </organization>
  </contributor>
  <edition>0</edition>
  <language>en</language>
  <script>Latn</script>
  <place>Gaithersburg, MD</place>
  <ext>
    <doctype>standard</doctype>
  </ext>
</bibdata>