<bibdata type="standard">
  <title type="title-main" format="text/plain" language="en" script="Latn">On the calculation of critical points by the method of Heidemann and Khalil</title>
  <title type="main" format="text/plain" language="en" script="Latn">On the calculation of critical points by the method of Heidemann and Khalil</title>
  <uri type="doi">https://nvlpubs.nist.gov/nistpubs/Legacy/TN/nbstechnicalnote1313.pdf</uri>
  <docidentifier type="NIST">NBS TN 1313</docidentifier>
  <docidentifier type="DOI">10.6028/NBS.TN.1313</docidentifier>
  <date type="published">
    <on>1988-01</on>
  </date>
  <contributor>
    <role type="author"/>
    <person>
      <name>
        <forename language="en" script="Latn">Brian</forename>
        <forename language="en" script="Latn">Eric</forename>
        <surname language="en" script="Latn">Eaton</surname>
      </name>
    </person>
  </contributor>
  <contributor>
    <role type="publisher"/>
    <organization>
      <name>National Bureau of Standards</name>
      <abbreviation>NBS</abbreviation>
    </organization>
  </contributor>
  <edition>0</edition>
  <language>en</language>
  <script>Latn</script>
  <place>Gaithersburg, MD</place>
  <ext>
    <doctype>standard</doctype>
  </ext>
</bibdata>