<bibdata type="standard">
  <title type="title-main" format="text/plain" language="en" script="Latn">Calculated and measured S₁₁, S₂₁, and group delay for simple types of coaxial and rectangular waveguide 2-port standards</title>
  <title type="main" format="text/plain" language="en" script="Latn">Calculated and measured S₁₁, S₂₁, and group delay for simple types of coaxial and rectangular waveguide 2-port standards</title>
  <uri type="doi">https://nvlpubs.nist.gov/nistpubs/Legacy/TN/nbstechnicalnote657.pdf</uri>
  <docidentifier type="NIST">NBS TN 657</docidentifier>
  <docidentifier type="DOI">10.6028/NBS.TN.657</docidentifier>
  <date type="published">
    <on>1974-01</on>
  </date>
  <contributor>
    <role type="author"/>
    <person>
      <name>
        <forename language="en" script="Latn">Robert</forename>
        <forename language="en" script="Latn">William</forename>
        <surname language="en" script="Latn">Beatty</surname>
      </name>
    </person>
  </contributor>
  <contributor>
    <role type="publisher"/>
    <organization>
      <name>National Bureau of Standards</name>
      <abbreviation>NBS</abbreviation>
    </organization>
  </contributor>
  <edition>0</edition>
  <language>en</language>
  <script>Latn</script>
  <place>Gaithersburg, MD</place>
  <ext>
    <doctype>standard</doctype>
  </ext>
</bibdata>