<bibdata type="standard">
  <title type="title-main" format="text/plain" language="en" script="Latn">Fire safety study of air ducts and fire dampers effect of hangar spacing, hangar size, and wall thickness: first progress report</title>
  <title type="main" format="text/plain" language="en" script="Latn">Fire safety study of air ducts and fire dampers effect of hangar spacing, hangar size, and wall thickness: first progress report</title>
  <uri type="doi">https://nvlpubs.nist.gov/nistpubs/Legacy/RPT/nbsreport10482.pdf</uri>
  <docidentifier type="NIST">NBS RPT 10482</docidentifier>
  <docidentifier type="DOI">10.6028/NBS.RPT.10482</docidentifier>
  <date type="published">
    <on>1971-01</on>
  </date>
  <contributor>
    <role type="author"/>
    <person>
      <name>
        <forename script="Latn">Lionel</forename>
        <surname script="Latn">Issen</surname>
      </name>
    </person>
  </contributor>
  <contributor>
    <role type="publisher"/>
    <organization>
      <name>National Bureau of Standards</name>
      <abbreviation>NBS</abbreviation>
    </organization>
  </contributor>
  <language/>
  <script>Latn</script>
  <place>Gaithersburg, MD</place>
  <ext>
    <doctype>standard</doctype>
  </ext>
</bibdata>