<bibdata type="standard">
  <title type="title-main" format="text/plain" language="en" script="Latn">NBS reactor : summary of activities, October 1971 to September 1972</title>
  <title type="main" format="text/plain" language="en" script="Latn">NBS reactor : summary of activities, October 1971 to September 1972</title>
  <uri type="doi">https://nvlpubs.nist.gov/nistpubs/Legacy/TN/nbstechnicalnote758.pdf</uri>
  <docidentifier type="NIST">NBS TN 758</docidentifier>
  <docidentifier type="DOI">10.6028/NBS.TN.758</docidentifier>
  <date type="published">
    <on>1973-01</on>
  </date>
  <contributor>
    <role type="editor"/>
    <person>
      <name>
        <forename language="en" script="Latn">Robert</forename>
        <surname language="en" script="Latn">Carter</surname>
      </name>
    </person>
  </contributor>
  <contributor>
    <role type="publisher"/>
    <organization>
      <name>National Bureau of Standards</name>
      <abbreviation>NIST</abbreviation>
    </organization>
  </contributor>
  <edition>0</edition>
  <language>en</language>
  <script>Latn</script>
  <place>Gaithersburg, MD</place>
  <ext>
    <doctype>standard</doctype>
  </ext>
</bibdata>