<bibdata type="standard">
  <title type="title-main" format="text/plain" language="en" script="Latn">Mission Critical Voice Start-of-Word Correction for Access Delay Measurement System</title>
  <title type="main" format="text/plain" language="en" script="Latn">Mission Critical Voice Start-of-Word Correction for Access Delay Measurement System</title>
  <uri type="doi">https://nvlpubs.nist.gov/nistpubs/TechnicalNotes/NIST.TN.2166.pdf</uri>
  <docidentifier type="NIST">NIST TN 2166</docidentifier>
  <docidentifier type="DOI">10.6028/NIST.TN.2166</docidentifier>
  <date type="published">
    <on>2021-07</on>
  </date>
  <contributor>
    <role type="author"/>
    <person>
      <name>
        <forename script="Latn">William</forename>
        <surname script="Latn">Magrogan</surname>
      </name>
    </person>
  </contributor>
  <contributor>
    <role type="author"/>
    <person>
      <name>
        <forename script="Latn">Jaden</forename>
        <surname script="Latn">Pieper</surname>
      </name>
    </person>
  </contributor>
  <contributor>
    <role type="author"/>
    <person>
      <name>
        <forename script="Latn">Zainab</forename>
        <surname script="Latn">Soetan</surname>
      </name>
    </person>
  </contributor>
  <contributor>
    <role type="publisher"/>
    <organization>
      <name>National Institute of Standards and Technology</name>
      <abbreviation>NIST</abbreviation>
    </organization>
  </contributor>
  <language/>
  <script>Latn</script>
  <place>Gaithersburg, MD</place>
  <ext>
    <doctype>standard</doctype>
  </ext>
</bibdata>