<bibdata type="standard">
  <title type="title-main" format="text/plain" language="en" script="Latn">A collection of technical studies completed for the Computer-aided Acquisition and Logistic Support (CALS) program: fiscal year 1988 volume 1 of 3, text, security and data management</title>
  <title type="main" format="text/plain" language="en" script="Latn">A collection of technical studies completed for the Computer-aided Acquisition and Logistic Support (CALS) program: fiscal year 1988 volume 1 of 3, text, security and data management</title>
  <uri type="doi">https://nvlpubs.nist.gov/nistpubs/Legacy/IR/nistir4315.pdf</uri>
  <docidentifier type="NIST">NIST IR 4315</docidentifier>
  <docidentifier type="DOI">10.6028/NIST.IR.4315</docidentifier>
  <date type="published">
    <on>1990-01</on>
  </date>
  <contributor>
    <role type="author"/>
    <person>
      <name>
        <forename script="Latn">Roy</forename>
        <surname script="Latn">Morgan</surname>
      </name>
    </person>
  </contributor>
  <contributor>
    <role type="publisher"/>
    <organization>
      <name>National Institute of Standards and Technology</name>
      <abbreviation>NIST</abbreviation>
    </organization>
  </contributor>
  <language/>
  <script>Latn</script>
  <place>Gaithersburg, MD</place>
  <ext>
    <doctype>standard</doctype>
  </ext>
</bibdata>