<bibdata type="standard">
  <title type="title-intro" format="text/plain" language="en" script="Latn">Requirements and conformance test assertions for ANSI/NIST-ITL 1-2011 record type 18</title>
  <title type="title-main" format="text/plain" language="en" script="Latn">DNA record</title>
  <title type="main" format="text/plain" language="en" script="Latn">Requirements and conformance test assertions for ANSI/NIST-ITL 1-2011 record type 18 - DNA record</title>
  <uri type="doi">https://nvlpubs.nist.gov/nistpubs/ir/2013/NIST.IR.7933.pdf</uri>
  <docidentifier type="NIST">NIST IR 7933</docidentifier>
  <docidentifier type="DOI">10.6028/NIST.IR.7933</docidentifier>
  <date type="published">
    <on>2013-05</on>
  </date>
  <contributor>
    <role type="author"/>
    <person>
      <name>
        <forename script="Latn">Fernando</forename>
        <surname script="Latn">Podio</surname>
      </name>
    </person>
  </contributor>
  <contributor>
    <role type="author"/>
    <person>
      <name>
        <forename script="Latn">Dylan</forename>
        <surname script="Latn">Yaga</surname>
      </name>
    </person>
  </contributor>
  <contributor>
    <role type="author"/>
    <person>
      <name>
        <forename script="Latn">Christofer</forename>
        <surname script="Latn">McGinnis</surname>
      </name>
    </person>
  </contributor>
  <contributor>
    <role type="publisher"/>
    <organization>
      <name>National Institute of Standards and Technology</name>
      <abbreviation>NIST</abbreviation>
    </organization>
  </contributor>
  <language/>
  <script>Latn</script>
  <place>Gaithersburg, MD</place>
  <ext>
    <doctype>standard</doctype>
  </ext>
</bibdata>