<bibdata type="standard">
  <title type="title-main" format="text/plain" language="en" script="Latn">Examining Recent HR Data for Gender Bias Among Federal Employees at NIST</title>
  <title type="main" format="text/plain" language="en" script="Latn">Examining Recent HR Data for Gender Bias Among Federal Employees at NIST</title>
  <uri type="doi">https://nvlpubs.nist.gov/nistpubs/ir/2021/NIST.IR.8363.pdf</uri>
  <docidentifier type="NIST">NISTIR 8363</docidentifier>
  <docidentifier type="DOI">10.6028/NIST.IR.8363</docidentifier>
  <date type="published">
    <on>2021-03</on>
  </date>
  <contributor>
    <role type="author"/>
    <person>
      <name>
        <forename script="Latn">Jasmine</forename>
        <surname script="Latn">Evans</surname>
      </name>
    </person>
  </contributor>
  <contributor>
    <role type="author"/>
    <person>
      <name>
        <forename script="Latn">Amanda</forename>
        <surname script="Latn">Koepke</surname>
      </name>
    </person>
  </contributor>
  <contributor>
    <role type="author"/>
    <person>
      <name>
        <forename script="Latn">Steven</forename>
        <surname script="Latn">Lund</surname>
      </name>
    </person>
  </contributor>
  <contributor>
    <role type="author"/>
    <person>
      <name>
        <forename script="Latn">Mary</forename>
        <surname script="Latn">Theofanos</surname>
      </name>
    </person>
  </contributor>
  <contributor>
    <role type="publisher"/>
    <organization>
      <name>National Institute of Standards and Technology</name>
      <abbreviation>NIST</abbreviation>
    </organization>
  </contributor>
  <language/>
  <script>Latn</script>
  <place>Gaithersburg, MD</place>
  <ext>
    <doctype>standard</doctype>
  </ext>
</bibdata>