<bibdata type="standard">
  <title type="title-main" format="text/plain" language="en" script="Latn">Summary report on the industry forum for monitoring, diagnostics, and prognostics for manufacturing operations</title>
  <title type="main" format="text/plain" language="en" script="Latn">Summary report on the industry forum for monitoring, diagnostics, and prognostics for manufacturing operations</title>
  <uri type="doi">https://nvlpubs.nist.gov/nistpubs/ams/NIST.AMS.100-23.pdf</uri>
  <docidentifier type="NIST">NIST AMS 100-23</docidentifier>
  <docidentifier type="DOI">10.6028/NIST.AMS.100-23</docidentifier>
  <date type="published">
    <on>2019-04</on>
  </date>
  <contributor>
    <role type="author"/>
    <person>
      <name>
        <forename script="Latn">Brian</forename>
        <surname script="Latn">Weiss</surname>
      </name>
    </person>
  </contributor>
  <contributor>
    <role type="author"/>
    <person>
      <name>
        <forename script="Latn">Michael</forename>
        <surname script="Latn">Brundage</surname>
      </name>
    </person>
  </contributor>
  <contributor>
    <role type="author"/>
    <person>
      <name>
        <forename script="Latn">Yannick</forename>
        <surname script="Latn">Tamm</surname>
      </name>
    </person>
  </contributor>
  <contributor>
    <role type="author"/>
    <person>
      <name>
        <forename script="Latn">Tommi</forename>
        <surname script="Latn">Makila</surname>
      </name>
    </person>
  </contributor>
  <contributor>
    <role type="author"/>
    <person>
      <name>
        <forename script="Latn">Joan</forename>
        <surname script="Latn">Pellegrino</surname>
      </name>
    </person>
  </contributor>
  <contributor>
    <role type="publisher"/>
    <organization>
      <name>National Institute of Standards and Technology</name>
      <abbreviation>NIST</abbreviation>
    </organization>
  </contributor>
  <language/>
  <script>Latn</script>
  <place>Gaithersburg, MD</place>
  <ext>
    <doctype>standard</doctype>
  </ext>
</bibdata>