<bibdata type="standard">
  <title type="title-main" format="text/plain" language="en" script="Latn">Final report of the e-SRM committee on the optimal delivery of services to customers for standard reference materials</title>
  <title type="main" format="text/plain" language="en" script="Latn">Final report of the e-SRM committee on the optimal delivery of services to customers for standard reference materials</title>
  <uri type="doi">https://nvlpubs.nist.gov/nistpubs/Legacy/IR/nistir6759.pdf</uri>
  <docidentifier type="NIST">NIST IR 6759</docidentifier>
  <docidentifier type="DOI">10.6028/NIST.IR.6759</docidentifier>
  <date type="published">
    <on>2001-01</on>
  </date>
  <contributor>
    <role type="author"/>
    <person>
      <name>
        <forename script="Latn">Sally</forename>
        <surname script="Latn">Bruce</surname>
      </name>
    </person>
  </contributor>
  <contributor>
    <role type="author"/>
    <person>
      <name>
        <forename script="Latn">Donna</forename>
        <surname script="Latn">Clarke</surname>
      </name>
    </person>
  </contributor>
  <contributor>
    <role type="author"/>
    <person>
      <name>
        <forename script="Latn">James</forename>
        <surname script="Latn">Ehrstein</surname>
      </name>
    </person>
  </contributor>
  <contributor>
    <role type="author"/>
    <person>
      <name>
        <forename script="Latn">Michael</forename>
        <surname script="Latn">Epstein</surname>
      </name>
    </person>
  </contributor>
  <contributor>
    <role type="author"/>
    <person>
      <name>
        <forename script="Latn">Dale</forename>
        <surname script="Latn">Friend</surname>
      </name>
    </person>
  </contributor>
  <contributor>
    <role type="author"/>
    <person>
      <name>
        <forename script="Latn">Thomas</forename>
        <surname script="Latn">Gills</surname>
      </name>
    </person>
  </contributor>
  <contributor>
    <role type="author"/>
    <person>
      <name>
        <forename script="Latn">Kenneth</forename>
        <surname script="Latn">Inn</surname>
      </name>
    </person>
  </contributor>
  <contributor>
    <role type="author"/>
    <person>
      <name>
        <forename script="Latn">Larry</forename>
        <surname script="Latn">Lucas</surname>
      </name>
    </person>
  </contributor>
  <contributor>
    <role type="author"/>
    <person>
      <name>
        <forename script="Latn">James</forename>
        <surname script="Latn">Potzick</surname>
      </name>
    </person>
  </contributor>
  <contributor>
    <role type="author"/>
    <person>
      <name>
        <forename script="Latn">Mary</forename>
        <surname script="Latn">Saunders</surname>
      </name>
    </person>
  </contributor>
  <contributor>
    <role type="author"/>
    <person>
      <name>
        <forename script="Latn">Nancy</forename>
        <surname script="Latn">Trahey</surname>
      </name>
    </person>
  </contributor>
  <contributor>
    <role type="author"/>
    <person>
      <name>
        <forename script="Latn">John</forename>
        <surname script="Latn">Travis</surname>
      </name>
    </person>
  </contributor>
  <contributor>
    <role type="author"/>
    <person>
      <name>
        <forename script="Latn">Gilbert</forename>
        <surname script="Latn">Ugiansky</surname>
      </name>
    </person>
  </contributor>
  <contributor>
    <role type="author"/>
    <person>
      <name>
        <forename script="Latn">Michael</forename>
        <surname script="Latn">Verkouteren</surname>
      </name>
    </person>
  </contributor>
  <contributor>
    <role type="author"/>
    <person>
      <name>
        <forename script="Latn">Daniel</forename>
        <surname script="Latn">Vigliotti</surname>
      </name>
    </person>
  </contributor>
  <contributor>
    <role type="author"/>
    <person>
      <name>
        <forename script="Latn">Robert</forename>
        <forename script="Latn">Jr</forename>
        <surname script="Latn">Watters</surname>
      </name>
    </person>
  </contributor>
  <contributor>
    <role type="publisher"/>
    <organization>
      <name>National Institute of Standards and Technology</name>
      <abbreviation>NIST</abbreviation>
    </organization>
  </contributor>
  <language/>
  <script>Latn</script>
  <place>Gaithersburg, MD</place>
  <ext>
    <doctype>standard</doctype>
  </ext>
</bibdata>