<bibdata type="standard">
  <title type="title-main" format="text/plain" language="en" script="Latn">Modeling and Conformance Testing for the Engineering Information Integration Standard ISO 15926</title>
  <title type="main" format="text/plain" language="en" script="Latn">Modeling and Conformance Testing for the Engineering Information Integration Standard ISO 15926</title>
  <uri type="doi">https://nvlpubs.nist.gov/nistpubs/ir/2013/NIST.IR.7917.pdf</uri>
  <docidentifier type="NIST">NIST IR 7917</docidentifier>
  <docidentifier type="DOI">10.6028/NIST.IR.7917</docidentifier>
  <date type="published">
    <on>2013-02</on>
  </date>
  <contributor>
    <role type="author"/>
    <person>
      <name>
        <forename language="en" script="Latn">Peter</forename>
        <surname language="en" script="Latn">Denno</surname>
      </name>
    </person>
  </contributor>
  <contributor>
    <role type="author"/>
    <person>
      <name>
        <forename language="en" script="Latn">Mark</forename>
        <surname language="en" script="Latn">Palmer</surname>
      </name>
    </person>
  </contributor>
  <contributor>
    <role type="publisher"/>
    <organization>
      <name>National Institute of Standards and Technology</name>
      <abbreviation>NIST</abbreviation>
    </organization>
  </contributor>
  <language>en</language>
  <script>Latn</script>
  <place>Gaithersburg, MD</place>
  <ext>
    <doctype>standard</doctype>
  </ext>
</bibdata>