<bibdata type="standard">
  <title type="title-main" format="text/plain" language="en" script="Latn">A study to determine the most important parameters for evaluating the resistance of soft body armor to penetration by edged weapons</title>
  <title type="main" format="text/plain" language="en" script="Latn">A study to determine the most important parameters for evaluating the resistance of soft body armor to penetration by edged weapons</title>
  <uri type="doi">https://nvlpubs.nist.gov/nistpubs/Legacy/IR/nistir4895.pdf</uri>
  <docidentifier type="NIST">NIST IR 4895</docidentifier>
  <docidentifier type="DOI">10.6028/NIST.IR.4895</docidentifier>
  <date type="published">
    <on>1993-01</on>
  </date>
  <contributor>
    <role type="author"/>
    <person>
      <name>
        <forename script="Latn">Nicholas</forename>
        <surname script="Latn">Calvano</surname>
      </name>
    </person>
  </contributor>
  <contributor>
    <role type="publisher"/>
    <organization>
      <name>National Institute of Standards and Technology</name>
      <abbreviation>NIST</abbreviation>
    </organization>
  </contributor>
  <language/>
  <script>Latn</script>
  <place>Gaithersburg, MD</place>
  <ext>
    <doctype>standard</doctype>
  </ext>
</bibdata>