<bibdata type="standard">
  <title type="title-main" format="text/plain" language="en" script="Latn">Measurement needs for fire safety: proceedings of an international workshop</title>
  <title type="main" format="text/plain" language="en" script="Latn">Measurement needs for fire safety: proceedings of an international workshop</title>
  <uri type="doi">https://nvlpubs.nist.gov/nistpubs/Legacy/IR/nistir6527.pdf</uri>
  <docidentifier type="NIST">NIST IR 6527</docidentifier>
  <docidentifier type="DOI">10.6028/NIST.IR.6527</docidentifier>
  <date type="published">
    <on>2000-01</on>
  </date>
  <contributor>
    <role type="author"/>
    <person>
      <name>
        <surname script="Latn">Ohlemiller</surname>
      </name>
    </person>
  </contributor>
  <contributor>
    <role type="author"/>
    <person>
      <name>
        <forename script="Latn">Erik</forename>
        <surname script="Latn">Johnsson</surname>
      </name>
    </person>
  </contributor>
  <contributor>
    <role type="author"/>
    <person>
      <name>
        <forename script="Latn">Richard</forename>
        <surname script="Latn">Gann</surname>
      </name>
    </person>
  </contributor>
  <contributor>
    <role type="publisher"/>
    <organization>
      <name>National Institute of Standards and Technology</name>
      <abbreviation>NIST</abbreviation>
    </organization>
  </contributor>
  <language/>
  <script>Latn</script>
  <place>Gaithersburg, MD</place>
  <ext>
    <doctype>standard</doctype>
  </ext>
</bibdata>